boar/__init__.py
boar/SIMsalabim_utils/CalcFom.py
boar/SIMsalabim_utils/CleanFolder.py
boar/SIMsalabim_utils/CompileProg.py
boar/SIMsalabim_utils/Download_SIMsalabim.py
boar/SIMsalabim_utils/GetInputPar.py
boar/SIMsalabim_utils/MakeDevParFile.py
boar/SIMsalabim_utils/PlotInputPar.py
boar/SIMsalabim_utils/RunSim.py
boar/SIMsalabim_utils/SimSS_plots.py
boar/SIMsalabim_utils/ZimT_plots.py
boar/SIMsalabim_utils/__init__.py
boar/SIMsalabim_utils/aux_func.py
boar/SIMsalabim_utils/plot_settings_screen.py
boar/SIMsalabim_utils/tVG_gen.py
boar/agents/Agent.py
boar/agents/DD_agents.py
boar/agents/NonIdealDiode_agents.py
boar/agents/TAS_agent.py
boar/agents/TrMC_agent.py
boar/agents/TrPL_agent.py
boar/agents/TranferMatrix_agent.py
boar/agents/__init__.py
boar/core/FitParams.py
boar/core/__init__.py
boar/core/funcs.py
boar/core/optimization.py
boar/core/optimization_botorch.py
boar/core/optimizer.py
boar/dynamic_utils/__init__.py
boar/dynamic_utils/pump.py
boar/dynamic_utils/rate_eq.py
boar_pv-1.0.10.dist-info/LICENSE.txt
boar_pv-1.0.10.dist-info/METADATA
boar_pv-1.0.10.dist-info/WHEEL
boar_pv-1.0.10.dist-info/top_level.txt
boar_pv-1.0.10.dist-info/RECORD
