Metadata-Version: 2.1
Name: boar-pv
Version: 1.0.10
Summary: High throughput parameter extraction and experimental design with Bayesian optimization
Home-page: https://github.com/i-MEET/boar
Download-URL: https://github.com/i-MEET/boar/archive/refs/tags/v1.0.7.tar.gz
Author: Vincent Le Corre, Larry Lueer
Author-email: vincent.le.corre@fau.de
License: BSD 3-Clause License
Keywords: Bayesian optimization,parameter extraction,experimental design,high throughput,solar cells
Classifier: Programming Language :: Python :: 3
Classifier: Intended Audience :: Science/Research
Classifier: Operating System :: OS Independent
Classifier: License :: OSI Approved :: BSD License
Requires-Python: >=3.9, <3.12
License-File: LICENSE.txt
Requires-Dist: numpy (>=1.2)
Requires-Dist: pandas (>=1.4)
Requires-Dist: matplotlib (>=3.5)
Requires-Dist: notebook (>=6.0)
Requires-Dist: jupyterlab (>=3.4)
Requires-Dist: ipympl (>=0.9)
Requires-Dist: seaborn (>=0.11)
Requires-Dist: scipy (>=1.0)
Requires-Dist: scikit-optimize (>=0.9)
Requires-Dist: tqdm (>=4.65)
Requires-Dist: parmap (>=1.5)
Requires-Dist: torch (>=2.0)
Requires-Dist: torchvision (>=0.15)
Requires-Dist: torchaudio (>=2.0)
Requires-Dist: ax-platform (>=0.3)
Requires-Dist: gitpython (>=3.1)
Requires-Dist: pyodbc (>=4.0)
Requires-Dist: openpyxl (>=3.0)
Provides-Extra: dev
Requires-Dist: pytest ; extra == 'dev'
Requires-Dist: twine ; extra == 'dev'
